{
  "Name": "Magic Shoes",
  "Desc": "Shoes with magical power sealed in them. After putting them on, you'll feel your mana has been enhanced.",
  "Rarity": 2,
  "Category": "Armor",
  "Subcategory": "Boot",
  "ItemInfo": {
    "Basic": {
      "Buyprice": 13000,
      "Sellprice": 6500,
      "BagLimit": 1,
      "NonExchangeable": 0
    },
    "Enchancment": {
      "EquipExp": 13000,
      "CharaExp": 0,
      "EnchantNeedRich": 0
    },
    "Effects": [],
    "Weapon": {
      "Category": "-",
      "IconName": "",
      "CanEquipNPC": 0,
      "ChargeSkillBattle": [],
      "ChargeSkillGather": [],
      "PassiveProperties": [],
      "ElemBonus": null,
      "LvupExpTypeId": 0
    },
    "Armor": {
      "CanEquipNPC": 1,
      "EquipAsShield": 1,
      "ChargeShield": [],
      "PassiveProperties": [],
      "ElemBonus": {
        "Fire": 0,
        "Water": 0,
        "Wind": 0,
        "Earth": 0,
        "Light": 0,
        "Shadow": 0
      },
      "LvupExpTypeId": 4241378302
    }
  },
  "Armor": {
    "CanEquipNPC": 1,
    "EquipAsShield": 1,
    "ChargeShield": [],
    "PassiveProperties": [],
    "ElemBonus": {
      "Fire": 0,
      "Water": 0,
      "Wind": 0,
      "Earth": 0,
      "Light": 0,
      "Shadow": 0
    },
    "LvupExpTypeId": 4241378302
  },
  "Resources": {
    "IcnFilename": "icn_itm606_0078_10default",
    "IcnAssetBundleId": 1863414131,
    "FullFilename": "",
    "FullAssetBundleId": 1398675703,
    "AtlasResID": 1007313192,
    "SpriteName": ""
  },
  "ParamIds": {
    "ObjId": 2081868624,
    "Uniqid": 2081868624,
    "Id": "OBJ_ITEM_GUARD_05360_00_00",
    "ResId": 1007313192,
    "ResIdIcon": 663119577,
    "ResswitchId": 3565975565,
    "ResswitchIdHQ": 2713337695,
    "ResActionId": 1007313192,
    "ObjTypeId": 3588665660,
    "ContentsTypeId": 4060084563,
    "NameId": 1276571111,
    "DescriptionId": 803909020,
    "CommonParamId": 588606868,
    "CharaParamId": 3819597731,
    "FacillityParamId": 856462509,
    "PickParamId": 2496751196,
    "FurnitureParamId": 1721008223,
    "GroundParamId": 1099520669,
    "ObjGroupId": 36203498,
    "WeaponParamId": 2915301859,
    "GuardParamId": 2572731432,
    "NormalParamId": 6165372,
    "ImportantParamId": 3170525707,
    "SpecialParamId": 527746145,
    "SurpriseboxParamId": 589680994,
    "GodItemParamId": 2401570819
  }
}