{
  "Name": "Fashionista Shoes",
  "Desc": "One of the pieces of heroic equipment made for Tailors. Fashion starts with the feet.",
  "Rarity": 3,
  "Category": "Armor",
  "Subcategory": "Boot",
  "ItemInfo": {
    "Basic": {
      "Buyprice": 10400,
      "Sellprice": 5200,
      "BagLimit": 1,
      "NonExchangeable": 0
    },
    "Enchancment": {
      "EquipExp": 10400,
      "CharaExp": 0,
      "EnchantNeedRich": 0
    },
    "Weapon": {
      "Category": "-",
      "IconName": "",
      "CanEquipNPC": 0,
      "ChargeSkillBattle": [],
      "ChargeSkillGather": [],
      "PassiveProperties": [],
      "ElemBonus": null,
      "LvupExpTypeId": 0
    },
    "Armor": {
      "CanEquipNPC": 1,
      "EquipAsShield": 1,
      "ChargeShield": [],
      "PassiveProperties": [],
      "ElemBonus": {
        "Fire": 0,
        "Water": 0,
        "Wind": 0,
        "Earth": 0,
        "Light": 0,
        "Shadow": 0
      },
      "LvupExpTypeId": 2345237352
    },
    "Effects": []
  },
  "Armor": {
    "CanEquipNPC": 1,
    "EquipAsShield": 1,
    "ChargeShield": [],
    "PassiveProperties": [],
    "ElemBonus": {
      "Fire": 0,
      "Water": 0,
      "Wind": 0,
      "Earth": 0,
      "Light": 0,
      "Shadow": 0
    },
    "LvupExpTypeId": 2345237352
  },
  "Resources": {
    "IcnFilename": "icn_itm606_0030_10default",
    "IcnAssetBundleId": 3549600084,
    "FullFilename": "",
    "FullAssetBundleId": 1398675703,
    "AtlasResID": 1007313192,
    "SpriteName": ""
  },
  "ParamIds": {
    "ObjId": 3230999415,
    "Uniqid": 3230999415,
    "Id": "OBJ_ITEM_GUARD_04900_00_00",
    "ResId": 1007313192,
    "ResIdIcon": 2600832766,
    "ResswitchId": 1745850410,
    "ResswitchIdHQ": 2713337695,
    "ResActionId": 1007313192,
    "ObjTypeId": 3588665660,
    "ContentsTypeId": 4060084563,
    "NameId": 4036298176,
    "DescriptionId": 2473149883,
    "CommonParamId": 2677441971,
    "CharaParamId": 3819597731,
    "FacillityParamId": 856462509,
    "PickParamId": 2496751196,
    "FurnitureParamId": 1721008223,
    "GroundParamId": 1099520669,
    "ObjGroupId": 36203498,
    "WeaponParamId": 2915301859,
    "GuardParamId": 635120655,
    "NormalParamId": 6165372,
    "ImportantParamId": 3170525707,
    "SpecialParamId": 527746145,
    "SurpriseboxParamId": 589680994,
    "GodItemParamId": 2401570819
  }
}