{
  "ChestName": "Goldmeer Valuables",
  "ChestRarity": 4,
  "Drops": [
    {
      "Name": "Plain Armor Core (S)",
      "ItemCount": 1,
      "ProbabilityPercent": 10.0,
      "Weight": 10.0,
      "Priority": 1,
      "DropRareTag": "Rare"
    },
    {
      "Name": "King Mutton",
      "ItemCount": 1,
      "ProbabilityPercent": 30.0,
      "Weight": 30.0,
      "Priority": 2,
      "DropRareTag": ""
    },
    {
      "Name": "Mutton",
      "ItemCount": 2,
      "ProbabilityPercent": 60.0,
      "Weight": 60.0,
      "Priority": 3,
      "DropRareTag": ""
    }
  ],
  "SurpriseboxObjId": 4132137598
}{
  "ChestName": "Goldmeer Valuables",
  "ChestRarity": 4,
  "Drops": [
    {
      "Name": "Plain Armor Core (M)",
      "ItemCount": 1,
      "ProbabilityPercent": 10.0,
      "Weight": 10.0,
      "Priority": 1,
      "DropRareTag": "Rare"
    },
    {
      "Name": "King Mutton",
      "ItemCount": 1,
      "ProbabilityPercent": 30.0,
      "Weight": 30.0,
      "Priority": 2,
      "DropRareTag": ""
    },
    {
      "Name": "Mutton",
      "ItemCount": 2,
      "ProbabilityPercent": 60.0,
      "Weight": 60.0,
      "Priority": 3,
      "DropRareTag": ""
    }
  ],
  "SurpriseboxObjId": 4128774909
}