{
  "Name": "Frymaster 2000",
  "Desc": "A pot that can be used to make dishes that the gods enjoy.\r No matter what kind of cooking, it can be done flawlessly.",
  "Rarity": 3,
  "Category": "Tool",
  "Subcategory": "Frying Pan",
  "ItemInfo": {
    "Basic": {
      "Buyprice": 36000,
      "Sellprice": 18000,
      "BagLimit": 1,
      "NonExchangeable": 0
    },
    "Enchancment": {
      "EquipExp": 36000,
      "CharaExp": 0,
      "EnchantNeedRich": 0
    },
    "Weapon": {
      "Category": "Frying Pan",
      "IconName": "icn_eqslot_flypan",
      "CanEquipNPC": 1,
      "ChargeSkillBattle": [],
      "ChargeSkillGather": [],
      "PassiveProperties": [],
      "ElemBonus": {
        "Fire": 0,
        "Water": 0,
        "Wind": 0,
        "Earth": 0,
        "Light": 0,
        "Shadow": 0
      },
      "LvupExpTypeId": 2345237352
    },
    "Armor": {
      "CanEquipNPC": 0,
      "EquipAsShield": 0,
      "ChargeShield": [],
      "PassiveProperties": [],
      "ElemBonus": {
        "Fire": 0,
        "Water": 0,
        "Wind": 0,
        "Earth": 0,
        "Light": 0,
        "Shadow": 0
      },
      "LvupExpTypeId": 4199345978
    },
    "Effects": []
  },
  "Weapon": {
    "Category": "Frying Pan",
    "IconName": "icn_eqslot_flypan",
    "CanEquipNPC": 1,
    "ChargeSkillBattle": [],
    "ChargeSkillGather": [],
    "PassiveProperties": [],
    "ElemBonus": {
      "Fire": 0,
      "Water": 0,
      "Wind": 0,
      "Earth": 0,
      "Light": 0,
      "Shadow": 0
    },
    "LvupExpTypeId": 2345237352
  },
  "Resources": {
    "IcnFilename": "icn_itm511_0009_10default",
    "IcnAssetBundleId": 3200050243,
    "FullFilename": "at00787_Pan00",
    "FullAssetBundleId": 3200050243,
    "AtlasResID": 1007313192,
    "SpriteName": ""
  },
  "ParamIds": {
    "ObjId": 3583938907,
    "Uniqid": 3583938907,
    "Id": "OBJ_ITEM_TOOL_01010_00_00",
    "ResId": 1075244903,
    "ResIdIcon": 2610759140,
    "ResswitchId": 2713337695,
    "ResswitchIdHQ": 2713337695,
    "ResActionId": 1007313192,
    "ObjTypeId": 3188418170,
    "ContentsTypeId": 1709142060,
    "NameId": 1615318964,
    "DescriptionId": 2590731689,
    "CommonParamId": 3551550818,
    "CharaParamId": 3819597731,
    "FacillityParamId": 856462509,
    "PickParamId": 2496751196,
    "FurnitureParamId": 1721008223,
    "GroundParamId": 1099520669,
    "ObjGroupId": 36203498,
    "WeaponParamId": 697256561,
    "GuardParamId": 3875797836,
    "NormalParamId": 6165372,
    "ImportantParamId": 3170525707,
    "SpecialParamId": 527746145,
    "SurpriseboxParamId": 589680994,
    "GodItemParamId": 2401570819
  }
}