{
  "Name": "Giant Pseudo Oak",
  "Title": "",
  "Desc": "A great tree that has absorbed plenty of sunlight. It swings its trunk to knock enemies away.",
  "Rarity": 1,
  "CharInfo": {
    "Attribute": "",
    "CV": "-",
    "DefaultCharge": {
      "ChargeLevel": 1,
      "SpCost": 0,
      "Name": "--------",
      "Desc": "-",
      "Attribute": "",
      "AwakenLvDamageMultiplier": {
        "5": 1.0
      },
      "NearComboCount": 0,
      "FarComboCount": 0
    },
    "Skillboard": [],
    "EpisodeText": "-",
    "OtherText": [
      "Reserved line. Won't be used.",
      "Reserved line. Won't be used.",
      "Reserved line. Won't be used.",
      "Reserved line. Won't be used.",
      "Reserved line. Won't be used.",
      "Reserved line. Won't be used.",
      "Reserved line. Won't be used."
    ]
  },
  "Resources": {
    "IcnFilename": "icn_mon026_0004",
    "IcnAssetBundleId": 2663909996,
    "FullFilename": "mon026_0004",
    "FullAssetBundleId": 2663909996,
    "AtlasResID": 1007313192,
    "SpriteName": ""
  },
  "ParamIds": {
    "ObjId": 2386566138,
    "Uniqid": 2386566138,
    "Id": "OBJ_CHARA_20073_00_00",
    "ResId": 668064693,
    "ResIdIcon": 4038125015,
    "ResswitchId": 2713337695,
    "ResswitchIdHQ": 2713337695,
    "ResActionId": 2777093845,
    "ObjTypeId": 4222102461,
    "ContentsTypeId": 1453935802,
    "NameId": 3875273717,
    "DescriptionId": 2474761200,
    "CommonParamId": 3637891532,
    "CharaParamId": 1654159472,
    "FacillityParamId": 856462509,
    "PickParamId": 2496751196,
    "FurnitureParamId": 1721008223,
    "GroundParamId": 1099520669,
    "ObjGroupId": 36203498,
    "WeaponParamId": 2915301859,
    "GuardParamId": 3875797836,
    "NormalParamId": 6165372,
    "ImportantParamId": 3170525707,
    "SpecialParamId": 527746145,
    "SurpriseboxParamId": 589680994,
    "GodItemParamId": 2401570819
  },
  "Category": "Tree"
}{
  "Name": "Giant Pseudo Oak",
  "Title": "",
  "Desc": "A great tree that has absorbed plenty of sunlight. It swings its trunk to knock enemies away.",
  "Rarity": 1,
  "CharInfo": {
    "Attribute": "",
    "CV": "-",
    "DefaultCharge": {
      "ChargeLevel": 1,
      "SpCost": 0,
      "Name": "--------",
      "Desc": "-",
      "Attribute": "",
      "AwakenLvDamageMultiplier": {
        "5": 1.0
      },
      "NearComboCount": 0,
      "FarComboCount": 0
    },
    "Skillboard": [],
    "EpisodeText": "-",
    "OtherText": [
      "Reserved line. Won't be used.",
      "Reserved line. Won't be used.",
      "Reserved line. Won't be used.",
      "Reserved line. Won't be used.",
      "Reserved line. Won't be used.",
      "Reserved line. Won't be used.",
      "Reserved line. Won't be used."
    ]
  },
  "Resources": {
    "IcnFilename": "icn_mon026_0004",
    "IcnAssetBundleId": 2663909996,
    "FullFilename": "mon026_0004",
    "FullAssetBundleId": 2663909996,
    "AtlasResID": 1007313192,
    "SpriteName": ""
  },
  "ParamIds": {
    "ObjId": 922516639,
    "Uniqid": 922516639,
    "Id": "OBJ_CHARA_20073_01_00",
    "ResId": 668064693,
    "ResIdIcon": 4038125015,
    "ResswitchId": 2713337695,
    "ResswitchIdHQ": 2713337695,
    "ResActionId": 2777093845,
    "ObjTypeId": 4222102461,
    "ContentsTypeId": 1453935802,
    "NameId": 3875273717,
    "DescriptionId": 2474761200,
    "CommonParamId": 3637891532,
    "CharaParamId": 1654159472,
    "FacillityParamId": 856462509,
    "PickParamId": 2496751196,
    "FurnitureParamId": 1721008223,
    "GroundParamId": 1099520669,
    "ObjGroupId": 36203498,
    "WeaponParamId": 2915301859,
    "GuardParamId": 3875797836,
    "NormalParamId": 6165372,
    "ImportantParamId": 3170525707,
    "SpecialParamId": 527746145,
    "SurpriseboxParamId": 589680994,
    "GodItemParamId": 2401570819
  },
  "Category": "Tree"
}{
  "Name": "Giant Pseudo Oak",
  "Title": "",
  "Desc": "Large Pseudo Oak (description)",
  "Rarity": 1,
  "CharInfo": {
    "Attribute": "",
    "CV": "-",
    "DefaultCharge": {
      "ChargeLevel": 1,
      "SpCost": 0,
      "Name": "--------",
      "Desc": "-",
      "Attribute": "",
      "AwakenLvDamageMultiplier": {
        "5": 1.0
      },
      "NearComboCount": 0,
      "FarComboCount": 0
    },
    "Skillboard": [],
    "EpisodeText": "-",
    "OtherText": [
      "Reserved line. Won't be used.",
      "Reserved line. Won't be used.",
      "Reserved line. Won't be used.",
      "Reserved line. Won't be used.",
      "Reserved line. Won't be used.",
      "Reserved line. Won't be used.",
      "Reserved line. Won't be used."
    ]
  },
  "Resources": {
    "IcnFilename": "icn_mon026_0004",
    "IcnAssetBundleId": 2663909996,
    "FullFilename": "mon026_0004",
    "FullAssetBundleId": 2663909996,
    "AtlasResID": 1007313192,
    "SpriteName": ""
  },
  "ParamIds": {
    "ObjId": 2633348116,
    "Uniqid": 2633348116,
    "Id": "OBJ_CHARA_20073_03_00",
    "ResId": 668064693,
    "ResIdIcon": 4038125015,
    "ResswitchId": 2713337695,
    "ResswitchIdHQ": 2713337695,
    "ResActionId": 2777093845,
    "ObjTypeId": 4222102461,
    "ContentsTypeId": 1453935802,
    "NameId": 4098774043,
    "DescriptionId": 2167698462,
    "CommonParamId": 3395321378,
    "CharaParamId": 1654159472,
    "FacillityParamId": 856462509,
    "PickParamId": 2496751196,
    "FurnitureParamId": 1721008223,
    "GroundParamId": 1099520669,
    "ObjGroupId": 36203498,
    "WeaponParamId": 2915301859,
    "GuardParamId": 3875797836,
    "NormalParamId": 6165372,
    "ImportantParamId": 3170525707,
    "SpecialParamId": 527746145,
    "SurpriseboxParamId": 589680994,
    "GodItemParamId": 2401570819
  },
  "Category": "Tree"
}