{
  "Name": "Weedling King",
  "Title": "",
  "Desc": "An overgrown plant that has received much sunlight and water. It'll turn its surroundings into a wilderness of weeds.",
  "Rarity": 1,
  "CharInfo": {
    "Attribute": "",
    "CV": "-",
    "DefaultCharge": {
      "ChargeLevel": 1,
      "SpCost": 0,
      "Name": "--------",
      "Desc": "-",
      "Attribute": "",
      "AwakenLvDamageMultiplier": {},
      "NearComboCount": 0,
      "FarComboCount": 0
    },
    "Skillboard": [],
    "EpisodeText": "-",
    "OtherText": []
  },
  "Resources": {
    "IcnFilename": "icn_mon022_0006",
    "IcnAssetBundleId": 156703557,
    "FullFilename": "mon022_0006",
    "FullAssetBundleId": 156703557,
    "AtlasResID": 1007313192,
    "SpriteName": ""
  },
  "ParamIds": {
    "ObjId": 434047699,
    "Uniqid": 434047699,
    "Id": "OBJ_CHARA_20071_00_00",
    "ResId": 2957953692,
    "ResIdIcon": 1731196158,
    "ResswitchId": 2713337695,
    "ResswitchIdHQ": 2713337695,
    "ResActionId": 840435708,
    "ObjTypeId": 4222102461,
    "ContentsTypeId": 1453935802,
    "NameId": 1902439132,
    "DescriptionId": 69126873,
    "CommonParamId": 1330299109,
    "CharaParamId": 4110903641,
    "FacillityParamId": 856462509,
    "PickParamId": 2496751196,
    "FurnitureParamId": 1721008223,
    "GroundParamId": 1099520669,
    "ObjGroupId": 36203498,
    "WeaponParamId": 2915301859,
    "GuardParamId": 3875797836,
    "NormalParamId": 6165372,
    "ImportantParamId": 3170525707,
    "SpecialParamId": 527746145,
    "SurpriseboxParamId": 589680994,
    "GodItemParamId": 2401570819
  },
  "Category": "Plant"
}{
  "Name": "Weedling King",
  "Title": "",
  "Desc": "An overgrown plant that has received much sunlight and water. It'll turn its surroundings into a wilderness of weeds.",
  "Rarity": 1,
  "CharInfo": {
    "Attribute": "",
    "CV": "-",
    "DefaultCharge": {
      "ChargeLevel": 1,
      "SpCost": 0,
      "Name": "--------",
      "Desc": "-",
      "Attribute": "",
      "AwakenLvDamageMultiplier": {},
      "NearComboCount": 0,
      "FarComboCount": 0
    },
    "Skillboard": [],
    "EpisodeText": "-",
    "OtherText": []
  },
  "Resources": {
    "IcnFilename": "icn_mon022_0006",
    "IcnAssetBundleId": 156703557,
    "FullFilename": "mon022_0006",
    "FullAssetBundleId": 156703557,
    "AtlasResID": 1007313192,
    "SpriteName": ""
  },
  "ParamIds": {
    "ObjId": 4157697023,
    "Uniqid": 4157697023,
    "Id": "OBJ_CHARA_20071_00_02",
    "ResId": 2957953692,
    "ResIdIcon": 1731196158,
    "ResswitchId": 2713337695,
    "ResswitchIdHQ": 2713337695,
    "ResActionId": 3692455632,
    "ObjTypeId": 4222102461,
    "ContentsTypeId": 1453935802,
    "NameId": 1902439132,
    "DescriptionId": 69126873,
    "CommonParamId": 1330299109,
    "CharaParamId": 4110903641,
    "FacillityParamId": 856462509,
    "PickParamId": 2496751196,
    "FurnitureParamId": 1721008223,
    "GroundParamId": 1099520669,
    "ObjGroupId": 36203498,
    "WeaponParamId": 2915301859,
    "GuardParamId": 3875797836,
    "NormalParamId": 6165372,
    "ImportantParamId": 3170525707,
    "SpecialParamId": 527746145,
    "SurpriseboxParamId": 589680994,
    "GodItemParamId": 2401570819
  },
  "Category": "Plant"
}