{
  "Name": "Desert Headdress",
  "Desc": "The most suitable headgear to withstand scorching summers. A necessity for living in the desert.",
  "Rarity": 3,
  "Category": "Armor",
  "Subcategory": "Head",
  "ItemInfo": {
    "Basic": {
      "Buyprice": 1160,
      "Sellprice": 290,
      "BagLimit": 1,
      "NonExchangeable": 1
    },
    "Enchancment": {
      "EquipExp": 290,
      "CharaExp": 0,
      "EnchantNeedRich": 0
    },
    "Effects": [],
    "Weapon": {
      "Category": "-",
      "IconName": "",
      "CanEquipNPC": 0,
      "ChargeSkillBattle": [],
      "ChargeSkillGather": [],
      "PassiveProperties": [],
      "ElemBonus": null,
      "LvupExpTypeId": 0
    },
    "Armor": {
      "CanEquipNPC": 1,
      "EquipAsShield": 1,
      "ChargeShield": [],
      "PassiveProperties": [
        {
          "Slot": 2,
          "Name": "-",
          "Desc": "-",
          "Effects": []
        },
        {
          "Slot": 3,
          "Name": "-",
          "Desc": "-",
          "Effects": []
        }
      ],
      "ElemBonus": {
        "Fire": 0,
        "Water": 0,
        "Wind": 0,
        "Earth": 0,
        "Light": 0,
        "Shadow": 0
      },
      "LvupExpTypeId": 2345237352
    }
  },
  "Armor": {
    "CanEquipNPC": 1,
    "EquipAsShield": 1,
    "ChargeShield": [],
    "PassiveProperties": [
      {
        "Slot": 2,
        "Name": "-",
        "Desc": "-",
        "Effects": []
      },
      {
        "Slot": 3,
        "Name": "-",
        "Desc": "-",
        "Effects": []
      }
    ],
    "ElemBonus": {
      "Fire": 0,
      "Water": 0,
      "Wind": 0,
      "Earth": 0,
      "Light": 0,
      "Shadow": 0
    },
    "LvupExpTypeId": 2345237352
  },
  "Resources": {
    "IcnFilename": "icn_itm601_0068_10default",
    "IcnAssetBundleId": 4174628300,
    "FullFilename": "ae01125_Hat01_typeD",
    "FullAssetBundleId": 4174628300,
    "AtlasResID": 1007313192,
    "SpriteName": ""
  },
  "ParamIds": {
    "ObjId": 3956572143,
    "Uniqid": 3956572143,
    "Id": "OBJ_ITEM_GUARD_00480_00_00",
    "ResId": 3291384598,
    "ResIdIcon": 2957300326,
    "ResswitchId": 2713337695,
    "ResswitchIdHQ": 2713337695,
    "ResActionId": 1007313192,
    "ObjTypeId": 3588665660,
    "ContentsTypeId": 161754055,
    "NameId": 3688126808,
    "DescriptionId": 3089635619,
    "CommonParamId": 3034044715,
    "CharaParamId": 3819597731,
    "FacillityParamId": 856462509,
    "PickParamId": 2496751196,
    "FurnitureParamId": 1721008223,
    "GroundParamId": 1099520669,
    "ObjGroupId": 36203498,
    "WeaponParamId": 2915301859,
    "GuardParamId": 245002391,
    "NormalParamId": 6165372,
    "ImportantParamId": 3170525707,
    "SpecialParamId": 527746145,
    "SurpriseboxParamId": 589680994,
    "GodItemParamId": 2401570819
  }
}