{
  "Name": "Divine Bomb",
  "Desc": "A super powerful bomb that contains Divine Power.",
  "Rarity": 3,
  "Category": "",
  "Subcategory": "",
  "ItemInfo": {
    "Basic": {
      "Buyprice": 7000,
      "Sellprice": 3500,
      "BagLimit": 5,
      "NonExchangeable": 0
    },
    "Enchancment": {
      "EquipExp": 0,
      "CharaExp": 0,
      "EnchantNeedRich": 0
    },
    "Weapon": {
      "Category": "-",
      "IconName": "",
      "CanEquipNPC": 0,
      "ChargeSkillBattle": [],
      "ChargeSkillGather": [],
      "PassiveProperties": [],
      "ElemBonus": null,
      "LvupExpTypeId": 0
    },
    "Armor": {
      "CanEquipNPC": 0,
      "EquipAsShield": 0,
      "ChargeShield": [],
      "PassiveProperties": [],
      "ElemBonus": {
        "Fire": 0,
        "Water": 0,
        "Wind": 0,
        "Earth": 0,
        "Light": 0,
        "Shadow": 0
      },
      "LvupExpTypeId": 4199345978
    },
    "Effects": []
  },
  "Resources": {
    "IcnFilename": "icn_itm102_0040_10default",
    "IcnAssetBundleId": 2900337281,
    "FullFilename": "",
    "FullAssetBundleId": 1398675703,
    "AtlasResID": 1007313192,
    "SpriteName": ""
  },
  "ParamIds": {
    "ObjId": 246142025,
    "Uniqid": 246142025,
    "Id": "OBJ_ITEM_NORMAL_00284_00_00",
    "ResId": 1007313192,
    "ResIdIcon": 2593423200,
    "ResswitchId": 2713337695,
    "ResswitchIdHQ": 2713337695,
    "ResActionId": 1007313192,
    "ObjTypeId": 2804698770,
    "ContentsTypeId": 3266290501,
    "NameId": 1537143360,
    "DescriptionId": 2620040884,
    "CommonParamId": 2466107718,
    "CharaParamId": 3819597731,
    "FacillityParamId": 856462509,
    "PickParamId": 2496751196,
    "FurnitureParamId": 1721008223,
    "GroundParamId": 1099520669,
    "ObjGroupId": 36203498,
    "WeaponParamId": 2915301859,
    "GuardParamId": 3875797836,
    "NormalParamId": 1351639880,
    "ImportantParamId": 3170525707,
    "SpecialParamId": 527746145,
    "SurpriseboxParamId": 589680994,
    "GodItemParamId": 2401570819
  }
}{
  "Name": "Divine Bomb",
  "Desc": "-",
  "Rarity": 1,
  "Category": "",
  "Subcategory": "",
  "ItemInfo": {
    "Basic": {
      "Buyprice": 0,
      "Sellprice": 0,
      "BagLimit": 1,
      "NonExchangeable": 0
    },
    "Enchancment": {
      "EquipExp": 0,
      "CharaExp": 0,
      "EnchantNeedRich": 0
    },
    "Weapon": {
      "Category": "-",
      "IconName": "",
      "CanEquipNPC": 0,
      "ChargeSkillBattle": [],
      "ChargeSkillGather": [],
      "PassiveProperties": [],
      "ElemBonus": null,
      "LvupExpTypeId": 0
    },
    "Armor": {
      "CanEquipNPC": 0,
      "EquipAsShield": 0,
      "ChargeShield": [],
      "PassiveProperties": [],
      "ElemBonus": {
        "Fire": 0,
        "Water": 0,
        "Wind": 0,
        "Earth": 0,
        "Light": 0,
        "Shadow": 0
      },
      "LvupExpTypeId": 4199345978
    },
    "Effects": []
  },
  "Resources": {
    "IcnFilename": "dummy",
    "IcnAssetBundleId": 1398675703,
    "FullFilename": "lit009_0008",
    "FullAssetBundleId": 1273117413,
    "AtlasResID": 1007313192,
    "SpriteName": ""
  },
  "ParamIds": {
    "ObjId": 2772687935,
    "Uniqid": 2772687935,
    "Id": "OBJ_LIT_00028_00_00",
    "ResId": 3939246056,
    "ResIdIcon": 421136110,
    "ResswitchId": 2713337695,
    "ResswitchIdHQ": 2713337695,
    "ResActionId": 787015096,
    "ObjTypeId": 2737538726,
    "ContentsTypeId": 1453935802,
    "NameId": 2060030145,
    "DescriptionId": 4260187921,
    "CommonParamId": 2772699533,
    "CharaParamId": 3819597731,
    "FacillityParamId": 856462509,
    "PickParamId": 2496751196,
    "FurnitureParamId": 1721008223,
    "GroundParamId": 1099520669,
    "ObjGroupId": 36203498,
    "WeaponParamId": 2915301859,
    "GuardParamId": 3875797836,
    "NormalParamId": 6165372,
    "ImportantParamId": 3170525707,
    "SpecialParamId": 527746145,
    "SurpriseboxParamId": 589680994,
    "GodItemParamId": 2401570819
  }
}