{
  "TableCollectionChara": [
    {
      "CollectionCharaInd": 1517094641,
      "ContentsId": 1517094641,
      "ShowFlg": 1,
      "CollectionNo": 17,
      "UnlockFlg": 0
    },
    {
      "CollectionCharaInd": 711470104,
      "ContentsId": 711470104,
      "ShowFlg": 1,
      "CollectionNo": 36,
      "UnlockFlg": 0
    },
    {
      "CollectionCharaInd": 3378256968,
      "ContentsId": 3378256968,
      "ShowFlg": 1,
      "CollectionNo": 70,
      "UnlockFlg": 0
    },
    {
      "CollectionCharaInd": 22550342,
      "ContentsId": 22550342,
      "ShowFlg": 1,
      "CollectionNo": 23,
      "UnlockFlg": 0
    },
    {
      "CollectionCharaInd": 2743146338,
      "ContentsId": 2743146338,
      "ShowFlg": 1,
      "CollectionNo": 61,
      "UnlockFlg": 0
    },
    {
      "CollectionCharaInd": 1878905874,
      "ContentsId": 1878905874,
      "ShowFlg": 1,
      "CollectionNo": 16,
      "UnlockFlg": 0
    },
    {
      "CollectionCharaInd": 968700875,
      "ContentsId": 968700875,
      "ShowFlg": 1,
      "CollectionNo": 20,
      "UnlockFlg": 0
    },
    {
      "CollectionCharaInd": 3685757667,
      "ContentsId": 3685757667,
      "ShowFlg": 1,
      "CollectionNo": 52,
      "UnlockFlg": 0
    },
    {
      "CollectionCharaInd": 297981250,
      "ContentsId": 297981250,
      "ShowFlg": 1,
      "CollectionNo": 3,
      "UnlockFlg": 0
    },
    {
      "CollectionCharaInd": 2917799403,
      "ContentsId": 2917799403,
      "ShowFlg": 1,
      "CollectionNo": 43,
      "UnlockFlg": 0
    },
    {
      "CollectionCharaInd": 2134261542,
      "ContentsId": 2134261542,
      "ShowFlg": 1,
      "CollectionNo": 71,
      "UnlockFlg": 0
    },
    {
      "CollectionCharaInd": 1353191400,
      "ContentsId": 1353191400,
      "ShowFlg": 1,
      "CollectionNo": 46,
      "UnlockFlg": 0
    },
    {
      "CollectionCharaInd": 4172547797,
      "ContentsId": 4172547797,
      "ShowFlg": 1,
      "CollectionNo": 53,
      "UnlockFlg": 0
    },
    {
      "CollectionCharaInd": 518086374,
      "ContentsId": 518086374,
      "ShowFlg": 1,
      "CollectionNo": 81,
      "UnlockFlg": 0
    },
    {
      "CollectionCharaInd": 3191802424,
      "ContentsId": 3191802424,
      "ShowFlg": 1,
      "CollectionNo": 26,
      "UnlockFlg": 0
    },
    {
      "CollectionCharaInd": 2456358399,
      "ContentsId": 2456358399,
      "ShowFlg": 1,
      "CollectionNo": 62,
      "UnlockFlg": 0
    },
    {
      "CollectionCharaInd": 1556371867,
      "ContentsId": 1556371867,
      "ShowFlg": 1,
      "CollectionNo": 59,
      "UnlockFlg": 0
    },
    {
      "CollectionCharaInd": 788872796,
      "ContentsId": 788872796,
      "ShowFlg": 1,
      "CollectionNo": 103,
      "UnlockFlg": 0
    },
    {
      "CollectionCharaInd": 3455195096,
      "ContentsId": 3455195096,
      "ShowFlg": 1,
      "CollectionNo": 19,
      "UnlockFlg": 0
    },
    {
      "CollectionCharaInd": 86040376,
      "ContentsId": 86040376,
      "ShowFlg": 1,
      "CollectionNo": 68,
      "UnlockFlg": 0
    },
    {
      "CollectionCharaInd": 2766613499,
      "ContentsId": 2766613499,
      "ShowFlg": 1,
      "CollectionNo": 48,
      "UnlockFlg": 0
    },
    {
      "CollectionCharaInd": 1950111180,
      "ContentsId": 1950111180,
      "ShowFlg": 1,
      "CollectionNo": 101,
      "UnlockFlg": 0
    },
    {
      "CollectionCharaInd": 1024669787,
      "ContentsId": 1024669787,
      "ShowFlg": 1,
      "CollectionNo": 54,
      "UnlockFlg": 0
    },
    {
      "CollectionCharaInd": 3785625631,
      "ContentsId": 3785625631,
      "ShowFlg": 1,
      "CollectionNo": 87,
      "UnlockFlg": 0
    },
    {
      "CollectionCharaInd": 387592829,
      "ContentsId": 387592829,
      "ShowFlg": 1,
      "CollectionNo": 78,
      "UnlockFlg": 0
    },
    {
      "CollectionCharaInd": 3013361592,
      "ContentsId": 3013361592,
      "ShowFlg": 1,
      "CollectionNo": 96,
      "UnlockFlg": 0
    },
    {
      "CollectionCharaInd": 2232555964,
      "ContentsId": 2232555964,
      "ShowFlg": 1,
      "CollectionNo": 39,
      "UnlockFlg": 0
    },
    {
      "CollectionCharaInd": 1428137061,
      "ContentsId": 1428137061,
      "ShowFlg": 1,
      "CollectionNo": 63,
      "UnlockFlg": 0
    },
    {
      "CollectionCharaInd": 4229565765,
      "ContentsId": 4229565765,
      "ShowFlg": 1,
      "CollectionNo": 18,
      "UnlockFlg": 0
    },
    {
      "CollectionCharaInd": 593826312,
      "ContentsId": 593826312,
      "ShowFlg": 1,
      "CollectionNo": 40,
      "UnlockFlg": 0
    },
    {
      "CollectionCharaInd": 3306216286,
      "ContentsId": 3306216286,
      "ShowFlg": 1,
      "CollectionNo": 8,
      "UnlockFlg": 0
    },
    {
      "CollectionCharaInd": 2607035375,
      "ContentsId": 2607035375,
      "ShowFlg": 1,
      "CollectionNo": 55,
      "UnlockFlg": 0
    },
    {
      "CollectionCharaInd": 1653088892,
      "ContentsId": 1653088892,
      "ShowFlg": 1,
      "CollectionNo": 25,
      "UnlockFlg": 0
    },
    {
      "CollectionCharaInd": 863517394,
      "ContentsId": 863517394,
      "ShowFlg": 1,
      "CollectionNo": 49,
      "UnlockFlg": 0
    },
    {
      "CollectionCharaInd": 3494644354,
      "ContentsId": 3494644354,
      "ShowFlg": 1,
      "CollectionNo": 88,
      "UnlockFlg": 0
    },
    {
      "CollectionCharaInd": 194846303,
      "ContentsId": 194846303,
      "ShowFlg": 1,
      "CollectionNo": 69,
      "UnlockFlg": 0
    },
    {
      "CollectionCharaInd": 2804882674,
      "ContentsId": 2804882674,
      "ShowFlg": 1,
      "CollectionNo": 24,
      "UnlockFlg": 0
    },
    {
      "CollectionCharaInd": 2018509759,
      "ContentsId": 2018509759,
      "ShowFlg": 1,
      "CollectionNo": 34,
      "UnlockFlg": 0
    },
    {
      "CollectionCharaInd": 1085613874,
      "ContentsId": 1085613874,
      "ShowFlg": 1,
      "CollectionNo": 76,
      "UnlockFlg": 0
    },
    {
      "CollectionCharaInd": 3903401487,
      "ContentsId": 3903401487,
      "ShowFlg": 1,
      "CollectionNo": 75,
      "UnlockFlg": 0
    },
    {
      "CollectionCharaInd": 461387397,
      "ContentsId": 461387397,
      "ShowFlg": 1,
      "CollectionNo": 86,
      "UnlockFlg": 0
    },
    {
      "CollectionCharaInd": 3082149622,
      "ContentsId": 3082149622,
      "ShowFlg": 1,
      "CollectionNo": 85,
      "UnlockFlg": 0
    },
    {
      "CollectionCharaInd": 2266320198,
      "ContentsId": 2266320198,
      "ShowFlg": 1,
      "CollectionNo": 41,
      "UnlockFlg": 0
    },
    {
      "CollectionCharaInd": 1503998456,
      "ContentsId": 1503998456,
      "ShowFlg": 1,
      "CollectionNo": 45,
      "UnlockFlg": 0
    },
    {
      "CollectionCharaInd": 698358545,
      "ContentsId": 698358545,
      "ShowFlg": 1,
      "CollectionNo": 28,
      "UnlockFlg": 0
    },
    {
      "CollectionCharaInd": 3370305518,
      "ContentsId": 3370305518,
      "ShowFlg": 1,
      "CollectionNo": 4,
      "UnlockFlg": 0
    },
    {
      "CollectionCharaInd": 2689146987,
      "ContentsId": 2689146987,
      "ShowFlg": 1,
      "CollectionNo": 97,
      "UnlockFlg": 0
    },
    {
      "CollectionCharaInd": 1770145942,
      "ContentsId": 1770145942,
      "ShowFlg": 1,
      "CollectionNo": 22,
      "UnlockFlg": 0
    },
    {
      "CollectionCharaInd": 907629233,
      "ContentsId": 907629233,
      "ShowFlg": 1,
      "CollectionNo": 73,
      "UnlockFlg": 0
    },
    {
      "CollectionCharaInd": 3644929170,
      "ContentsId": 3644929170,
      "ShowFlg": 1,
      "CollectionNo": 72,
      "UnlockFlg": 0
    },
    {
      "CollectionCharaInd": 289750940,
      "ContentsId": 289750940,
      "ShowFlg": 1,
      "CollectionNo": 32,
      "UnlockFlg": 0
    },
    {
      "CollectionCharaInd": 2886068093,
      "ContentsId": 2886068093,
      "ShowFlg": 1,
      "CollectionNo": 65,
      "UnlockFlg": 0
    },
    {
      "CollectionCharaInd": 2065686120,
      "ContentsId": 2065686120,
      "ShowFlg": 1,
      "CollectionNo": 1,
      "UnlockFlg": 0
    },
    {
      "CollectionCharaInd": 1205017515,
      "ContentsId": 1205017515,
      "ShowFlg": 1,
      "CollectionNo": 83,
      "UnlockFlg": 0
    },
    {
      "CollectionCharaInd": 4109943235,
      "ContentsId": 4109943235,
      "ShowFlg": 1,
      "CollectionNo": 10,
      "UnlockFlg": 0
    },
    {
      "CollectionCharaInd": 504826989,
      "ContentsId": 504826989,
      "ShowFlg": 1,
      "CollectionNo": 51,
      "UnlockFlg": 0
    },
    {
      "CollectionCharaInd": 3187096881,
      "ContentsId": 3187096881,
      "ShowFlg": 1,
      "CollectionNo": 37,
      "UnlockFlg": 0
    },
    {
      "CollectionCharaInd": 2413236389,
      "ContentsId": 2413236389,
      "ShowFlg": 1,
      "CollectionNo": 27,
      "UnlockFlg": 0
    },
    {
      "CollectionCharaInd": 1535308903,
      "ContentsId": 1535308903,
      "ShowFlg": 1,
      "CollectionNo": 12,
      "UnlockFlg": 0
    },
    {
      "CollectionCharaInd": 732385259,
      "ContentsId": 732385259,
      "ShowFlg": 1,
      "CollectionNo": 29,
      "UnlockFlg": 0
    },
    {
      "CollectionCharaInd": 3381321638,
      "ContentsId": 3381321638,
      "ShowFlg": 1,
      "CollectionNo": 15,
      "UnlockFlg": 0
    },
    {
      "CollectionCharaInd": 42999887,
      "ContentsId": 42999887,
      "ShowFlg": 1,
      "CollectionNo": 98,
      "UnlockFlg": 0
    },
    {
      "CollectionCharaInd": 2764552862,
      "ContentsId": 2764552862,
      "ShowFlg": 1,
      "CollectionNo": 11,
      "UnlockFlg": 0
    },
    {
      "CollectionCharaInd": 1901936047,
      "ContentsId": 1901936047,
      "ShowFlg": 1,
      "CollectionNo": 84,
      "UnlockFlg": 0
    },
    {
      "CollectionCharaInd": 980747458,
      "ContentsId": 980747458,
      "ShowFlg": 1,
      "CollectionNo": 42,
      "UnlockFlg": 0
    },
    {
      "CollectionCharaInd": 3727099915,
      "ContentsId": 3727099915,
      "ShowFlg": 1,
      "CollectionNo": 33,
      "UnlockFlg": 0
    },
    {
      "CollectionCharaInd": 371393285,
      "ContentsId": 371393285,
      "ShowFlg": 1,
      "CollectionNo": 93,
      "UnlockFlg": 0
    },
    {
      "CollectionCharaInd": 2921472738,
      "ContentsId": 2921472738,
      "ShowFlg": 1,
      "CollectionNo": 90,
      "UnlockFlg": 0
    },
    {
      "CollectionCharaInd": 2188649765,
      "ContentsId": 2188649765,
      "ShowFlg": 1,
      "CollectionNo": 99,
      "UnlockFlg": 0
    },
    {
      "CollectionCharaInd": 1385155191,
      "ContentsId": 1385155191,
      "ShowFlg": 1,
      "CollectionNo": 9,
      "UnlockFlg": 0
    },
    {
      "CollectionCharaInd": 4206055983,
      "ContentsId": 4206055983,
      "ShowFlg": 1,
      "CollectionNo": 58,
      "UnlockFlg": 0
    },
    {
      "CollectionCharaInd": 548218113,
      "ContentsId": 548218113,
      "ShowFlg": 1,
      "CollectionNo": 92,
      "UnlockFlg": 0
    },
    {
      "CollectionCharaInd": 3226542680,
      "ContentsId": 3226542680,
      "ShowFlg": 1,
      "CollectionNo": 77,
      "UnlockFlg": 0
    },
    {
      "CollectionCharaInd": 2480395865,
      "ContentsId": 2480395865,
      "ShowFlg": 1,
      "CollectionNo": 5,
      "UnlockFlg": 0
    },
    {
      "CollectionCharaInd": 1631589749,
      "ContentsId": 1631589749,
      "ShowFlg": 1,
      "CollectionNo": 47,
      "UnlockFlg": 0
    },
    {
      "CollectionCharaInd": 805246704,
      "ContentsId": 805246704,
      "ShowFlg": 1,
      "CollectionNo": 50,
      "UnlockFlg": 0
    },
    {
      "CollectionCharaInd": 3488957218,
      "ContentsId": 3488957218,
      "ShowFlg": 1,
      "CollectionNo": 66,
      "UnlockFlg": 0
    },
    {
      "CollectionCharaInd": 100015318,
      "ContentsId": 100015318,
      "ShowFlg": 1,
      "CollectionNo": 60,
      "UnlockFlg": 0
    },
    {
      "CollectionCharaInd": 2797661796,
      "ContentsId": 2797661796,
      "ShowFlg": 1,
      "CollectionNo": 82,
      "UnlockFlg": 0
    },
    {
      "CollectionCharaInd": 1983578422,
      "ContentsId": 1983578422,
      "ShowFlg": 1,
      "CollectionNo": 89,
      "UnlockFlg": 0
    },
    {
      "CollectionCharaInd": 1036385205,
      "ContentsId": 1036385205,
      "ShowFlg": 1,
      "CollectionNo": 14,
      "UnlockFlg": 0
    },
    {
      "CollectionCharaInd": 3873619427,
      "ContentsId": 3873619427,
      "ShowFlg": 1,
      "CollectionNo": 13,
      "UnlockFlg": 0
    },
    {
      "CollectionCharaInd": 448796637,
      "ContentsId": 448796637,
      "ShowFlg": 1,
      "CollectionNo": 94,
      "UnlockFlg": 0
    },
    {
      "CollectionCharaInd": 3036283681,
      "ContentsId": 3036283681,
      "ShowFlg": 1,
      "CollectionNo": 38,
      "UnlockFlg": 0
    },
    {
      "CollectionCharaInd": 2262445749,
      "ContentsId": 2262445749,
      "ShowFlg": 1,
      "CollectionNo": 31,
      "UnlockFlg": 0
    },
    {
      "CollectionCharaInd": 1481294702,
      "ContentsId": 1481294702,
      "ShowFlg": 1,
      "CollectionNo": 7,
      "UnlockFlg": 0
    },
    {
      "CollectionCharaInd": 4291967564,
      "ContentsId": 4291967564,
      "ShowFlg": 1,
      "CollectionNo": 44,
      "UnlockFlg": 0
    },
    {
      "CollectionCharaInd": 604188305,
      "ContentsId": 604188305,
      "ShowFlg": 1,
      "CollectionNo": 100,
      "UnlockFlg": 0
    },
    {
      "CollectionCharaInd": 3315465175,
      "ContentsId": 3315465175,
      "ShowFlg": 1,
      "CollectionNo": 95,
      "UnlockFlg": 0
    },
    {
      "CollectionCharaInd": 2680830079,
      "ContentsId": 2680830079,
      "ShowFlg": 1,
      "CollectionNo": 21,
      "UnlockFlg": 0
    },
    {
      "CollectionCharaInd": 1713777132,
      "ContentsId": 1713777132,
      "ShowFlg": 1,
      "CollectionNo": 79,
      "UnlockFlg": 0
    },
    {
      "CollectionCharaInd": 885573029,
      "ContentsId": 885573029,
      "ShowFlg": 1,
      "CollectionNo": 91,
      "UnlockFlg": 0
    },
    {
      "CollectionCharaInd": 3528154744,
      "ContentsId": 3528154744,
      "ShowFlg": 1,
      "CollectionNo": 102,
      "UnlockFlg": 0
    },
    {
      "CollectionCharaInd": 217785030,
      "ContentsId": 217785030,
      "ShowFlg": 1,
      "CollectionNo": 57,
      "UnlockFlg": 0
    },
    {
      "CollectionCharaInd": 2861312370,
      "ContentsId": 2861312370,
      "ShowFlg": 1,
      "CollectionNo": 56,
      "UnlockFlg": 0
    },
    {
      "CollectionCharaInd": 2031651474,
      "ContentsId": 2031651474,
      "ShowFlg": 1,
      "CollectionNo": 2,
      "UnlockFlg": 0
    },
    {
      "CollectionCharaInd": 1098532033,
      "ContentsId": 1098532033,
      "ShowFlg": 1,
      "CollectionNo": 74,
      "UnlockFlg": 0
    },
    {
      "CollectionCharaInd": 4023325334,
      "ContentsId": 4023325334,
      "ShowFlg": 1,
      "CollectionNo": 35,
      "UnlockFlg": 0
    },
    {
      "CollectionCharaInd": 484837916,
      "ContentsId": 484837916,
      "ShowFlg": 1,
      "CollectionNo": 64,
      "UnlockFlg": 0
    },
    {
      "CollectionCharaInd": 3096859986,
      "ContentsId": 3096859986,
      "ShowFlg": 1,
      "CollectionNo": 80,
      "UnlockFlg": 0
    },
    {
      "CollectionCharaInd": 2379236447,
      "ContentsId": 2379236447,
      "ShowFlg": 1,
      "CollectionNo": 30,
      "UnlockFlg": 0
    }
  ],
  "IdRef": {}
}